openaq/__init__.py
openaq/_async/__init__.py
openaq/_async/client.py
openaq/_async/transport.py
openaq/_async/models/__init__.py
openaq/_async/models/base.py
openaq/_async/models/countries.py
openaq/_async/models/instruments.py
openaq/_async/models/licenses.py
openaq/_async/models/locations.py
openaq/_async/models/manufacturers.py
openaq/_async/models/measurements.py
openaq/_async/models/owners.py
openaq/_async/models/parameters.py
openaq/_async/models/providers.py
openaq/_async/models/sensors.py
openaq/_sync/__init__.py
openaq/_sync/client.py
openaq/_sync/transport.py
openaq/_sync/models/__init__.py
openaq/_sync/models/base.py
openaq/_sync/models/countries.py
openaq/_sync/models/instruments.py
openaq/_sync/models/licenses.py
openaq/_sync/models/locations.py
openaq/_sync/models/manufacturers.py
openaq/_sync/models/measurements.py
openaq/_sync/models/owners.py
openaq/_sync/models/parameters.py
openaq/_sync/models/providers.py
openaq/_sync/models/sensors.py
openaq/shared/__init__.py
openaq/shared/client.py
openaq/shared/exceptions.py
openaq/shared/models.py
openaq/shared/responses.py
openaq/shared/transport.py
openaq/shared/types.py
openaq/vendor/humps.py
openaq-0.3.0.dist-info/METADATA
openaq-0.3.0.dist-info/WHEEL
openaq-0.3.0.dist-info/licenses/LICENSE
openaq-0.3.0.dist-info/RECORD
