Metadata-Version: 2.3
Name: openaq
Version: 0.3.0
Project-URL: Documentation, https://github.com/openaq/openaq-python#readme
Project-URL: Issues, https://github.com/openaq/openaq-python/issues
Project-URL: Source, https://github.com/openaq/openaq-python
Author-email: Russ Biggs <russ@openaq.org>, Gabe Fosse <gabe@openaq.org>
License-Expression: MIT
License-File: LICENSE
Classifier: Development Status :: 4 - Beta
Classifier: Programming Language :: Python
Classifier: Programming Language :: Python :: 3.8
Classifier: Programming Language :: Python :: 3.9
Classifier: Programming Language :: Python :: 3.10
Classifier: Programming Language :: Python :: 3.11
Classifier: Programming Language :: Python :: 3.12
Classifier: Programming Language :: Python :: Implementation :: CPython
Classifier: Programming Language :: Python :: Implementation :: PyPy
Requires-Python: >=3.8
Requires-Dist: httpx==0.25.0
Provides-Extra: all
Requires-Dist: orjson>=3.2.1; extra == 'all'
